tanzania_mno/__init__.py
tanzania_mno/validate.py
tanzania_mno-0.1.0.dist-info/LICENSE.txt
tanzania_mno-0.1.0.dist-info/METADATA
tanzania_mno-0.1.0.dist-info/WHEEL
tanzania_mno-0.1.0.dist-info/top_level.txt
tanzania_mno-0.1.0.dist-info/RECORD
